chaoxing/__init__.py
chaoxing/_account.py
chaoxing/_exceptions.py
chaoxing/_logging.py
chaoxing/_typing.py
chaoxing/_yzpan.py
chaoxing-0.1.1.dist-info/WHEEL
chaoxing-0.1.1.dist-info/METADATA
chaoxing-0.1.1.dist-info/RECORD
