Metadata-Version: 2.1
Name: chaoxing
Version: 0.1.1
Summary: 
Author: lisonge
Author-email: i@songe.li
Requires-Python: >=3.8,<4.0
Classifier: Programming Language :: Python :: 3
Classifier: Programming Language :: Python :: 3.8
Classifier: Programming Language :: Python :: 3.9
Requires-Dist: httpx (>=0.17.1,<0.18.0)
